pulumi_rabbitmq/__init__.py
pulumi_rabbitmq/_inputs.py
pulumi_rabbitmq/_utilities.py
pulumi_rabbitmq/binding.py
pulumi_rabbitmq/exchange.py
pulumi_rabbitmq/federation_upstream.py
pulumi_rabbitmq/get_default_user.py
pulumi_rabbitmq/get_exchange.py
pulumi_rabbitmq/get_user.py
pulumi_rabbitmq/get_v_host.py
pulumi_rabbitmq/operator_policy.py
pulumi_rabbitmq/outputs.py
pulumi_rabbitmq/permissions.py
pulumi_rabbitmq/policy.py
pulumi_rabbitmq/provider.py
pulumi_rabbitmq/pulumi-plugin.json
pulumi_rabbitmq/py.typed
pulumi_rabbitmq/queue.py
pulumi_rabbitmq/shovel.py
pulumi_rabbitmq/topic_permissions.py
pulumi_rabbitmq/user.py
pulumi_rabbitmq/v_host.py
pulumi_rabbitmq/config/__init__.py
pulumi_rabbitmq/config/__init__.pyi
pulumi_rabbitmq/config/vars.py
pulumi_rabbitmq-3.4.1.dist-info/METADATA
pulumi_rabbitmq-3.4.1.dist-info/WHEEL
pulumi_rabbitmq-3.4.1.dist-info/top_level.txt
pulumi_rabbitmq-3.4.1.dist-info/RECORD
